environ_composition/__init__.py
environ_composition/config.py
environ_composition/parser.py
environ_composition-1.1.1.dist-info/licenses/LICENSE
environ_composition-1.1.1.dist-info/METADATA
environ_composition-1.1.1.dist-info/WHEEL
environ_composition-1.1.1.dist-info/top_level.txt
environ_composition-1.1.1.dist-info/RECORD
