Metadata-Version: 2.4
Name: environ-composition
Version: 1.1.1
Summary: The library for creating nested environ configuration through composition
Author-email: Aleksei Fomenko <fomenko_ai@proton.me>
License: MIT
Project-URL: Homepage, https://github.com/fomenko-ai/environ-composition
Classifier: Programming Language :: Python :: 3
Classifier: License :: OSI Approved :: MIT License
Requires-Python: >=3.7
License-File: LICENSE
Dynamic: license-file
